qborsh/__init__.py
qborsh/constants.py
qborsh/utils.py
qborsh/csrc/py_borsh.pyi
qborsh/csrc/borsh.h
qborsh/csrc/py_borsh.pypy310-pp73-x86_64-linux-gnu.so
qborsh/csrc/__init__.py
qborsh/csrc/borsh.c
qborsh/csrc/py_borsh.c
qborsh/types/schema.py
qborsh/types/numeric.py
qborsh/types/strings.py
qborsh/types/__init__.py
qborsh/types/base.py
qborsh/types/collections.py
qborsh/types/helpers.py
qborsh-1.0.1.dist-info/METADATA
qborsh-1.0.1.dist-info/RECORD
qborsh-1.0.1.dist-info/top_level.txt
qborsh-1.0.1.dist-info/WHEEL
qborsh-1.0.1.dist-info/LICENSE
