Metadata-Version: 2.2
Name: qborsh
Version: 1.0.1
Summary: Borsh serialization for Python written in C.
Home-page: https://github.com/qvecs/qborsh
Author: Quick Vectors
Author-email: felipe@qvecs.com
Project-URL: Bug Tracker, https://github.com/qvecs/qborsh/issues
Project-URL: Source Code, https://github.com/qvecs/qborsh
Classifier: Programming Language :: Python :: 3
Classifier: Programming Language :: C
Classifier: Programming Language :: Python :: Implementation :: CPython
Classifier: License :: OSI Approved :: MIT License
Classifier: Operating System :: OS Independent
Classifier: Topic :: Utilities
Requires-Python: >=3.10
License-File: LICENSE
Requires-Dist: qbase58==1.0.4
Provides-Extra: dev
Requires-Dist: pytest; extra == "dev"
Dynamic: author
Dynamic: author-email
Dynamic: classifier
Dynamic: description
Dynamic: description-content-type
Dynamic: home-page
Dynamic: project-url
Dynamic: provides-extra
Dynamic: requires-dist
Dynamic: requires-python
Dynamic: summary
